[
    {
        "错误维度": ["知识性错误", "执行性错误"],
        "典型表现": ["公式错用", "计算失误"],
        "具体错误点": "在计算空气质量等级为1的概率时，错误地计算为0.28，而非正确的0.43。",
        "错误维度导致错误点出现原因": "学生可能对概率计算概念理解不够透彻（知识性错误），导致错用公式以至计算失误。此外，在查找频数时出现转抄错误（执行性错误），导致整个运算过程出错。",
        "main": 0,
        "index": 0
    },
    {
        "错误维度": ["策略性错误", "逻辑性错误"],
        "典型表现": ["缺乏整体观", "不等价变换"],
        "具体错误点": "在计算一天的平均锻炼人次时，错误地用所有中点值直接相加后除以3，得到错误答案134.33。",
        "错误维度导致错误点出现原因": "学生未能正确识别出每组频数的重要性，而过分依赖中点值（策略性错误），同时忽视了不同区间频数占比的影响（逻辑性错误），导致错误的计算方式和结果。",
        "main": 0,
        "index": 1
    },
    {
        "错误维度": ["执行性错误"],
        "典型表现": ["计算失误"],
        "具体错误点": "在计算列联表的K^2值时进行错误的算术运算，得到错误值K^2=3.241，而不是正确的K^2=5.820。",
        "错误维度导致错误点出现原因": "学生可能在计算过程中出现计算失误，漏乘、漏除或误操作是常见的原因，导致最终结果偏差，未能有效验证相关性。",
        "main": 0,
        "index": 2
    },
    {
        "错误维度": ["知识性错误"],
        "典型表现": ["概念混淆"],
        "具体错误点": "在判定空气质量是否与锻炼人次有关时，错误理解K^2值与临界值的关系，误认为K^2应大于10.828才有效。",
        "错误维度导致错误点出现原因": "学生对临界值表的概念混淆，未能准确理解K^2值对比临界值的方法，导致对结果结论产生重大误判。这是由于数学统计知识的必要前提条件被忽视或误记。",
        "main": 1,
        "index": 3
    }
]