[
    {
        "错误维度": ["知识性错误", "逻辑性错误"],
        "典型表现": ["概念混淆", "不等价变换"],
        "具体错误点": "学生在求离心率时错误地使用了公式，从而得到错误结果 e = 0.5。",
        "错误维度导致错误点出现原因": "由于学生对椭圆的离心率公式理解不深刻（知识性错误），导致在计算中未能正确识别“c”和“a”之间的关系（概念混淆）。同时，在变换方程解出离心率时，未能准确进行等价变换（逻辑性错误），错误地认为离心率可以简单地通过初级代入获得，从而导致错误结果。",
        "main": 0,
        "index": 0
    },
    {
        "错误维度": ["策略性错误", "执行性错误"],
        "典型表现": ["模式识别失败", "计算失误"],
        "具体错误点": "在验证 |PA| = |PB| 时，学生因为错误理解对称条件，计算中未能验证椭圆方程，结果给出错误的中心位置。",
        "错误维度导致错误点出现原因": "学生未能准确识别问题中的对称性要求（策略性错误），因此在验证点P满足 |PA| = |PB| 时，错误地考虑了点间距离条件，未结合直线AB的正确位置计算。加之计算过程中的不精确操作导致最终结果偏离正确答案（执行性错误），从而未正确得到椭圆中心的坐标。",
        "main": 1,
        "index": 1
    },
    {
        "错误维度": ["知识性错误"],
        "典型表现": ["公式错用"],
        "具体错误点": "学生在问题的第一部分计算椭圆的参数关系时误用了韦达定理公式，得出错误的参数比值 a:b=3:2。",
        "错误维度导致错误点出现原因": "学生对韦达定理的使用产生了知识性误解（知识性错误），未能联想起正确的参数间比值公式。同时，可能遗漏了椭圆轴长之间的关系特征，导致在通过程序简化时无法正确得出参数结果，从而给出了错误的比值。",
        "main": 0,
        "index": 2
    }
]