[
    {
        "错误维度": ["知识性错误", "执行性错误"],
        "典型表现": ["公式错用", "计算失误"],
        "具体错误点": "学生在将方程 $1+z=i-iz$ 转化为 $z=i$ 的过程中因执行错误算错了复数运算，错误地得到 $z=\\frac{1-i}{1+i}$ 为非单位复数，导致错选B（$\\sqrt{2}$）。",
        "错误维度导致错误点出现原因": "学生可能误记复数运算的性质，导致在计算中错用了公式。同时，学生在化简过程中出现计算失误，导致最终结果偏离正确答案。",
        "main": 0,
        "index": 0
    },
    {
        "错误维度": ["策略性错误", "逻辑性错误"],
        "典型表现": ["思维僵化", "偷换概念"],
        "具体错误点": "学生错误地认为 $\\frac{1+z}{1-z}=i$ 满足条件的复数一定是单位复数，直接选A，而未考虑完整的运算步骤。",
        "错误维度导致错误点出现原因": "由于学生思维僵化和偷换概念，他们可能完全依赖于复数运算的惯例性知识，误以为这种形式一定会给出单位复数，而忽视题目实际运算可能呈现的不同复数性质。",
        "main": 1,
        "index": 1
    },
    {
        "错误维度": ["知识性错误"],
        "典型表现": ["概念混淆"],
        "具体错误点": "在理解方程 $\\frac{1+z}{1-z}=i$ 时，学生混淆了复数与模的关系，错误计算为 $|z|=\\sqrt{3}$，选择C。",
        "错误维度导致错误点出现原因": "学生对复数模的计算理解不充分，混淆了复数计算中的运算结果与模的求解，认为解方程后模为其他选项的数值。",
        "main": 0,
        "index": 2
    },
    {
        "错误维度": ["执行性错误"],
        "典型表现": ["审题不清", "计算失误"],
        "具体错误点": "未完整地将方程化简，有可能做了一些计算步骤但得到 $|z|=2$，选择D。",
        "错误维度导致错误点出现原因": "审题时忽视了题目中的特殊设定，导致在解题过程中没有正确化简方程，粗心在计算阶段导致答案与实际情况不符。",
        "main": 0,
        "index": 3
    }
]