[
    {
        "错误维度": ["知识性错误", "策略性错误"],
        "典型表现": ["公式错用", "模式识别失败"],
        "具体错误点": "在处理 $C_{1}$ 的参数方程时，学生错误地将圆的标准方程记成了 $(x-5)^2 + (y-5)^2 = 25$，导致错误的极坐标方程。",
        "错误维度导致错误点出现原因": "由于学生对圆的标准方程公式不熟悉或者遗忘，从而错误地代入参数方程计算，导致其未能正确识别圆心位置及半径。同时，由于策略性障碍，他们未能识别出将参数方程转化为极坐标方程的正确过程，从而沿着错误的思路进行计算。",
        "main": 0,
        "index": 0
    },
    {
        "错误维度": ["逻辑性错误"],
        "典型表现": ["偷换概念"],
        "具体错误点": "在联立方程时，学生错误地认为可以直接将 $C_{2}$ 的极坐标方程 $\rho = 2 \sin \theta$ 转化为直角坐标方程 $x^2 + y^2 = 2y$ 而未考虑其完整性，导致丢失一些解。",
        "错误维度导致错误点出现原因": "学生在转化极坐标方程时犯下偷换概念的错误，未完整地处理极坐标到直角坐标的转换过程。他们错误地假定简单替换变量足够描述曲线的全部性质，而忽视了直接替换可能遗漏的几何性质和讨论范围，最终得到不完全且错误的解。",
        "main": 1,
        "index": 1
    },
    {
        "错误维度": ["执行性错误"],
        "典型表现": ["计算失误"],
        "具体错误点": "在计算交点的直角坐标时，学生求解方程组时出现了计算错误，导致计算出错误的交点坐标，例如误认为交点是 $(x=2, y=2)$。",
        "错误维度导致错误点出现原因": "学生可能在计算步骤中没有仔细检查自己的计算过程，导致在代入及计算过程中出错。审题不清和计算环节的疏漏导致其误解了最终结果，未能精确求解方程组。",
        "main": 0,
        "index": 2
    }
]