[
    {
        "错误维度": ["知识性错误", "逻辑性错误"],
        "典型表现": ["公式错用", "不等价变换"],
        "具体错误点": "学生错误地应用了坐标公式，得到 $M(\\frac{2\\cos\\alpha + \\cos 2\\alpha}{2}, \\frac{2\\sin\\alpha + \\sin 2\\alpha}{2})$。",
        "错误维度导致错误点出现原因": "由于学生对中点公式的理解不清晰（知识性错误），并且在使用中点公式时未能保持公式之后的变换等价性（逻辑性错误），导致错误地取平均值为中点坐标。",
        "main": 0,
        "index": 0
    },
    {
        "错误维度": ["策略性错误", "执行性错误"],
        "典型表现": ["思维僵化", "计算失误"],
        "具体错误点": "在计算 $M$ 点到坐标原点的距离时学生得到了错误的结果 $\\sqrt{2\\cos^2\\alpha + 2}$。",
        "错误维度导致错误点出现原因": "学生可能因在多次计算中抓住某形式化的模式而思维僵化（策略性错误），未能走出这种模式进行正确运算。同时因计算过程中未能准确切分和计算出平方项（执行性错误），导致错误结果。",
        "main": 0,
        "index": 1
    },
    {
        "错误维度": ["知识性错误", "执行性错误"],
        "典型表现": ["概念混淆", "审题不清"],
        "具体错误点": "无法得出 $M$ 的轨迹方程，学生错误判断为二分线 $x = y$。",
        "错误维度导致错误点出现原因": "学生在知识性方面对旋转参数曲线的概念混淆，因此无法正确理解题目中提供的曲线参数方程（知识性错误）。并且学生可能未清楚看出两个点$P$及$Q$的阵面变化对轨迹的影响（执行性错误），导致错误分析。",
        "main": 1,
        "index": 2
    },
    {
        "错误维度": ["逻辑性错误"],
        "典型表现": ["偷换概念"],
        "具体错误点": "学生认为因为 $\\sin(\\pi)=0$，于是错误地认为任何角度达到原点时均有可能。",
        "错误维度导致错误点出现原因": "学生误认为在证明轨迹过原点时，对于任何模拟证明角度都偷换成$\\sin$或$\\cos$为零即满足条件（逻辑性错误），未能意识到仅$\\alpha=\\pi$才能使得该情况成立。",
        "main": 0,
        "index": 3
    }
]