[
    {
        "错误维度": ["知识性错误", "执行性错误"],
        "典型表现": ["概念混淆", "计算失误"],
        "具体错误点": "学生在解决双曲线离心率的计算时，错误地认为$c = 2\\sqrt{5}a$，从而导致后续计算错误。",
        "错误维度导致错误点出现原因": "由于学生对离心率的定义理解不够深刻（概念混淆），认为离心率是形如$c = 2\\sqrt{5}a$的形式。在后续计算中，还由于在处理平方求解时未能准确简化（计算失误），导致整个解答过程连续错误，最终没有得到正确的$a$值。",
        "main": 0,
        "index": 0
    },
    {
        "错误维度": ["逻辑性错误", "策略性错误"],
        "典型表现": ["不等价变换", "缺乏整体观"],
        "具体错误点": "学生错误地将$\\left(|PF_{1}| - |PF_{2}|\\right)^2 + 2|PF_{1}||PF_{2}| = 4c^2$解读为$2c = c$，从而得出错误结论$a = 2$。",
        "错误维度导致错误点出现原因": "学生在代数变换中，错误地将式子化简为一般方程而没有考虑双曲线的几何特性（不等价变换）。由于没有意识到应该先整体理解问题的几何背景和性质（缺乏整体观），采用直接代入法，导致错误答案。",
        "main": 0,
        "index": 1
    },
    {
        "错误维度": ["策略性错误", "执行性错误"],
        "典型表现": ["模式识别失败", "审题不清"],
        "具体错误点": "学生在最后一步误解了题意，误认为三角形面积为8，从而错误地选择了答案C（a = 4）。",
        "错误维度导致错误点出现原因": "由于学生在读题时没有仔细理解题目要求和条件（审题不清），导致在问题求解的最后阶段错误的模式识别，直接导致错误的选项选择（模式识别失败），因而得出$a = 4$。",
        "main": 1,
        "index": 2
    }
]