[
    {
        "错误维度": ["知识性错误", "策略性错误"],
        "典型表现": ["性质误记", "缺乏整体观"],
        "具体错误点": "学生误认为直三棱柱的内切球半径是其高的一半，因此计算错误。",
        "错误维度导致错误点出现原因": "学生可能对三棱柱内切球的性质记忆错误（性质误记），并未能把直三棱柱的几何性质与球的性质进行整合理解（缺乏整体观）。因此，认为内切球半径为3/2的基础设置在于球直径要等于高，而非分析直三棱柱的特定几何构造，由此导致错误。",
        "main": 0,
        "index": 0
    },
    {
        "错误维度": ["逻辑性错误"],
        "典型表现": ["不等价变换"],
        "具体错误点": "学生在计算三角形ABC的内切圆半径时，错误计算为1。",
        "错误维度导致错误点出现原因": "由于对直三棱柱内角的关系未能准确推导，学生可能忽略了基本关系定理，以至于在求解过程中的不等价变换使得半径计算为错误值1，进而影响后续体积的判定。",
        "main": 1,
        "index": 1
    },
    {
        "错误维度": ["执行性错误"],
        "典型表现": ["计算失误"],
        "具体错误点": "学生在计算三角形$A B C$的内切圆半径时，将 $\\frac{6+8-10}{2}$ 计算为1而非2。",
        "错误维度导致错误点出现原因": "在计算具体步骤中，学生可能由于计算粗心或书写不规范，导致简单的加减运算出错。尽管思路正确，但由于计算失误，得到了错误结果。",
        "main": 0,
        "index": 2
    }
]