[
    {
        "错误维度": ["知识性错误", "逻辑性错误"],
        "典型表现": ["概念混淆", "不等价变换"],
        "具体错误点": "学生错误地认为函数 $y=x$ 的定义域和值域与 $y=10^{\\lg x}$ 相同，因此选择了选项 A 作为答案。",
        "错误维度导致错误点出现原因": "由于对函数的定义域和和值域的核心概念理解不够准确，学生可能混淆了不同函数的特性。在这种情况下，他未能正确识别出 $y=x$ 的定义域和值域为实数集 R，而不是 $(0,+∞)$。这可能也是因为在逻辑判断时，没有进行适当的等价变换和比较，导致他认为 A 是一个合适的选项。",
        "main": 0,
        "index": 0
    },
    {
        "错误维度": ["知识性错误"],
        "典型表现": ["性质误记"],
        "具体错误点": "学生错误地认为函数 $y=2^x$ 的值域与 $y=10^{\\lg x}$ 的值域相同，因此选择了选项 C 作为答案。",
        "错误维度导致错误点出现原因": "这可能是因为学生对指数函数的值域记忆错误，误记为与 $y=10^{\\lg x}$ 的值域相同是 $(0,+∞)$。缺乏对自然函数的特性理解导致他们无法辨识出 $y=2^x$ 定义域为 R，但值域为 $(0,+∞)$。",
        "main": 1,
        "index": 1
    },
    {
        "错误维度": ["知识性错误", "策略性错误"],
        "典型表现": ["公式错用", "模式识别失败"],
        "具体错误点": "学生错误地将函数 $y=\\lg x$ 选为答案，认为它的定义域和值域与 $y=10^{\\lg x}$ 相同。",
        "错误维度导致错误点出现原因": "学生可能错用对数函数的定义域和值域知识，误认为这两个函数的性质一致。同时在解题时未能正确识别出题目中要求的给定函数的特性与 $y=\\lg x$ 不同。由于策略性失误，未能采取分离定义域和值域作为分析标准，导致选出了错误答案。",
        "main": 0,
        "index": 2
    },
    {
        "错误维度": ["执行性错误"],
        "典型表现": ["审题不清"],
        "具体错误点": "学生无法给出答案，因为他未能准确审题并分析各选项的定义域和值域。",
        "错误维度导致错误点出现原因": "学生可能在解题时没有仔细审视问题要求，没有认真检查每个选项的定义域和值域。导致最终无法辨认出其中哪个选项与 $y=10^{\\lg x}$ 拥有相同的定义域和值域，陷入困惑而无法做出决策。",
        "main": 0,
        "index": 3
    }
]