[
    {
        "错误维度": ["知识性错误", "逻辑性错误"],
        "典型表现": ["公式错用", "不等价变换"],
        "具体错误点": "学生认为$f(x)$的最大值是2，而不是$\sqrt{2}$。",
        "错误维度导致错误点出现原因": "由于学生对三角函数的最大值求解公式理解不深刻，从而在转换成$\sqrt{2} \\sin \\left(\\frac{x}{3}+\\frac{\\pi}{4}\\right)$时误认为$\sin$的最大值1应用在这里得到的是2。同时忽视了$\sqrt{2}$前系数的影响，导致错误使用公式，错误地相信最终的最大值是2。",
        "main": 0,
        "index": 0
    },
    {
        "错误维度": ["执行性错误"],
        "典型表现": ["计算失误"],
        "具体错误点": "学生错误地计算了最小正周期为$3\\pi$。",
        "错误维度导致错误点出现原因": "学生在计算最小正周期时，由于对基本周期的倍数关系理解不准确，误以为是单纯的一个周期乘以3，直接使用了$\frac{2\\pi}{3}$，得到的时是错误的3倍关系，忽略了周期与因数的正确对应关系，错误地认为最小正周期是$3\\pi$。",
        "main": 1,
        "index": 1
    },
    {
        "错误维度": ["策略性错误"],
        "典型表现": ["思维僵化"],
        "具体错误点": "学生选择了D选项，因为他按照固定方式认为$f(x)$最大值是2。",
        "错误维度导致错误点出现原因": "学生习惯于固定思路，未能灵活识别题目中$f(x)=\\sin \\frac{x}{3}+\\cos \\frac{x}{3}$的形式转换，未能将其转化和简化为$f(x)=\\sqrt{2} \\sin \\left(\\frac{x}{3}+\\frac{\\pi}{4}\\right)$，因此错误地维持过去习得的思维模式，导致错误选择了最大值为2的选项D。",
        "main": 0,
        "index": 2
    }
]