[
    {
        "错误维度": ["知识性"],
        "典型表现": ["公式错用", "性质误记"],
        "具体错误点": "学生误以为偶函数仅在 y 轴对称性体现在正负号位置，不理解偶函数对任意 x 都有 f(-x)=f(x)。因此把 f(\\log_5 \\frac{1}{4}) 和 f(\\log_5 4) 错误地认为值不同，不使用偶函数的性质简化表达式，结果选 D 作为答案。",
        "错误维度导致错误点出现原因": "学生并未牢固掌握偶函数的本质定义，混淆了偶函数与其他对称性的函数（如周期函数），没有意识到 f(\\log_5 \\frac{1}{4}) = f(\\log_5 4)。知识储备的不足导致未能正确应用偶函数性质，直接比较原式而出现选项判断错误。",
        "main": 0,
        "index": 0
    },
    {
        "错误维度": ["逻辑性"],
        "典型表现": ["推理不严密", "不等价变换"],
        "具体错误点": "学生在比较函数值时，错误将指数与对数的顺序等同处理，认为 2^{-\\frac{3}{2}} < 2^{-\\frac{2}{3}} < \\log_5 \\frac{1}{4} 的数值大小，从而选择了 A。",
        "错误维度导致错误点出现原因": "学生在把对数和幂函数的数值转换时，用错了顺序或直接跳步推理，没有把不同形式的数值互相变换后再比较大小，逻辑链条断裂，导致出现比较错误。推理过程中忽视了基本不等式和数轴上的实际分布。",
        "main": 0,
        "index": 1
    },
    {
        "错误维度": ["策略性"],
        "典型表现": ["模式识别失败", "无法转化问题"],
        "具体错误点": "学生没有意识到应该将对数和指数全部统一化简为数字，未做对数换底和指数换算，直接生硬比较 f(\\log_8 \\frac{1}{4})、f(2^{-2/3})、f(2^{-3/2}) 的大小，导致答案无法判断或误选 B。",
        "错误维度导致错误点出现原因": "学生不能有效建立各个数学表达式之间的联系，没有意识到换底公式与指数换算可以简化问题，缺乏将问题统一化处理的策略，导致对各项函数输入无法做定量判断或顺序比较，失去了得到正确答案的关键环节。这种策略性缺失非常普遍。",
        "main": 1,
        "index": 2
    },
    {
        "错误维度": ["执行性"],
        "典型表现": ["计算失误"],
        "具体错误点": "学生在计算 \\log_5 \\frac{1}{4} 时，误算为 -0.5（实际上应为 -2/\\log_5 2），进而带入顺序比较得出选项 A。",
        "错误维度导致错误点出现原因": "在将 \\log_5 \\frac{1}{4} 进行计算时，可能把 \\frac{1}{4} 简单处理为 -0.5 或混淆对数与分数，直接带入比较大小顺序，忽略了换底或转化公式，属于典型的计算粗心与操作错误。",
        "main": 0,
        "index": 3
    },
    {
        "错误维度": ["知识性", "逻辑性"],
        "典型表现": ["性质误记", "分类讨论不完备"],
        "具体错误点": "学生认为 f(x) 在 (0,+∞) 单调递减，即对所有实数区间都单调递减，没有区分正负区间，直接将负数输入大小顺序原样照搬（如误判 f(-a)>f(-b) 只与 a,b 比较有关），选 D。",
        "错误维度导致错误点出现原因": "学生一方面未记牢函数单调性的定义（未明确只能在 (0,+∞) 用来比较）；另一方面逻辑上遗漏了偶函数性质使负输入可以看作正输入讨论，造成既理解定义错误，又实际操作中逻辑链条断裂，最终混淆两类区间的函数性状，产生复合型错误。",
        "main": 0,
        "index": 4
    },
    {
        "错误维度": ["策略性", "执行性"],
        "典型表现": ["思维僵化", "抄写错误"],
        "具体错误点": "学生在解题时，机械地将 \\log_5 \\frac{1}{4} 和 \\log_8 \\frac{1}{4} 误看成同一个表达式，导致顺序判断出错，最终选了 B 作为答案。",
        "错误维度导致错误点出现原因": "学生解题策略过于死板，只是机械比对选项结构，没有细致审题分辨底数、幂和输入的具体差异。同时，在实际操作时由于粗心抄错表达式，使算式走向完全错误。两种维度缺陷互叠加剧错误发生几率，导致直接误判选项。",
        "main": 0,
        "index": 5
    }
]