[
    {
        "错误维度": ["知识性错误", "逻辑性错误"],
        "典型表现": ["公式错用", "分类讨论不完备"],
        "具体错误点": "学生在找到双曲线焦点时误用圆锥曲线公式，错误认为焦点为 $(\sqrt{3m}, 0)$。",
        "错误维度导致错误点出现原因": "由于学生对双曲线的标准形式和焦点的求法存在知识性缺陷（公式错用），同时在逻辑推理上没有完整分析曲线参数的变化（分类讨论不完备），导致在计算焦点时，错误地应用了一般公式，导致错误的焦点坐标 $(\sqrt{3m}, 0)$。",
        "main": 0,
        "index": 0
    },
    {
        "错误维度": ["策略性错误", "执行性错误"],
        "典型表现": ["模式识别失败", "计算失误"],
        "具体错误点": "学生首先化简双曲线方程错误，认为其渐近线为 $x+\sqrt{3m} y=0$，最终距离公式计算出错，得到错误答案 $\\sqrt{3} m$。",
        "错误维度导致错误点出现原因": "由于学生未能正确识别双曲线的标准形式（模式识别失败），在化简双曲线方程时出现失误，导致后续使用的渐近线方程错误。此外，学生在距离公式的应用计算中出现了一些执行性错误（计算失误），从而得到错误答案 $\\sqrt{3} m$。",
        "main": 1,
        "index": 1
    },
    {
        "错误维度": ["执行性错误", "知识性错误"],
        "典型表现": ["审题不清", "概念混淆"],
        "具体错误点": "学生没有正确识别 C 的形式，误认为为 x 和 y 的替换后形式，导致错误计算渐近线，给出答案 D。",
        "错误维度导致错误点出现原因": "学生没有仔细审题（审题不清），在处理 x 和 y 时混淆了原始坐标和变换后的坐标。此外，学生对双曲线渐近线性质掌握不清（概念混淆），错误识别了方程和渐近线之间的关系，从而误选择答案 D。",
        "main": 0,
        "index": 2
    }
]