[
    {
        "错误维度": ["知识性错误", "执行性错误"],
        "典型表现": ["公式错用", "计算失误"],
        "具体错误点": "在计算 f'(x) 的时候，由于对导数的知识理解不足，学生错误地求f'(x)为 (2x + a + x^2 + ax -1)e^{x-1}，没有正确应用乘积法则。",
        "错误维度导致错误点出现原因": "由于学生对导数公式的概念理解不清（公式错用），涉及到较复杂的乘积及和的导数时出现混淆。同时在执行过程中出现了简单的计算失误，未能正确使用乘积法则进行正确计算。",
        "main": 0,
        "index": 0
    },
    {
        "错误维度": ["逻辑性错误", "策略性错误"],
        "典型表现": ["偷换概念", "无法转化问题"],
        "具体错误点": "在判定极值点时，对极值点的定义混淆，将 f'(x)=0 误解为 f(x) 的值直接得到，因此得到错误的函数值而没有进一步求最值。",
        "错误维度导致错误点出现原因": "学生在过程中偷换极值点与函数值的概念，误认为极值点是求解 f'(x)=0 的结果而不是进一步判定点是否确为极值。因此策略上未能通过找到导数等于零的点来判定极值，并错误理解问题导致错误选项。",
        "main": 1,
        "index": 1
    },
    {
        "错误维度": ["策略性错误"],
        "典型表现": ["缺乏整体观"],
        "具体错误点": "学生没有正确分析 f'(x)，以致无法正确寻找变化区间及确定极值点，从而对选项判断作出了错误选择。",
        "错误维度导致错误点出现原因": "学生在处理问题时未能认识到需要找到完整的导函数来分析 f(x) 的增减性，无法有效识别整体的函数行为，在选择过程中由于不清楚极值点的相关条件而发生选择错误。",
        "main": 0,
        "index": 2
    }
]