[
    {
        "错误维度": ["知识性错误", "逻辑性错误"],
        "典型表现": ["公式错用", "不等价变换"],
        "具体错误点": "学生在计算球的半径时误用了长方体的体积公式，导致错误地认为球的半径应该是 $3a$，从而得到错误的球面积为 $12 \\pi a^{2}$。",
        "错误维度导致错误点出现原因": "学生对球和长方体的性质理解不深，导致在计算球的半径时不小心使用了长方体的体积公式 $V=lwh$ 而非通过对角线来求球的外接半径。同时，对于球面积的公式变换不熟悉，错误地认为应用体积的三次方来计算面积，违背了几何上的基本概念间的逻辑关系，因此直接导致球的面积计算错误。",
        "main": 0,
        "index": 0
    },
    {
        "错误维度": ["策略性错误", "执行性错误"],
        "典型表现": ["缺乏整体观", "计算失误"],
        "具体错误点": "学生在计算球外接半径时，错误地算出了半径为 $\\sqrt{6}a$，最后错误地选择了选项 C(即球面积 $12 \\pi a^{2}$)。",
        "错误维度导致错误点出现原因": "学生可能在选择合适的方法来求解球半径时，未能清晰地构建长方体和球间的位置关系，缺乏整体观导致对几何概念不理解；此外，执行上有算数失误，未能正确简化对角线公式为球的半径通过平方求出为 $\\sqrt{3}a$，错误的运算使得其选择错误选项。",
        "main": 1,
        "index": 1
    },
    {
        "错误维度": ["知识性错误", "执行性错误"],
        "典型表现": ["概念混淆", "抄写错误"],
        "具体错误点": "学生在抄写题目和解题时混淆了半径和对边的关系，误将长方体的长和球的直径等同，导致得到错误的球面积为 $24 \\pi a^{2}$。",
        "错误维度导致错误点出现原因": "可能是由于学生对长方体和球之间关系的理解模糊，将长方体的最长对角线当作球的直径解，缺乏基础知识的巩固。同时，抄写题目数据时不小心错误记录了对角线的定义，导致在最后步骤计算中直接失误，最终得到错误的球面积。",
        "main": 0,
        "index": 2
    }
]