[
    {
        "错误维度": ["知识性"],
        "典型表现": ["概念混淆"],
        "具体错误点": "学生错误地认为只要有磁体存在，线圈中就一定会有感应电流，因而选择了A项作为正确答案。",
        "错误维度导致错误点出现原因": "学生对电磁感应的本质——感应电流的产生需要磁通量变化——理解不够，不清楚单纯放置磁体不产生感应电流，因此将“有磁体”与“有感应电流”直接对应，导致误选A项。",
        "main": 0,
        "index": 0
    },
    {
        "错误维度": ["逻辑性"],
        "典型表现": ["分类讨论不完备"],
        "具体错误点": "学生错误地选择C项，认为把条形磁铁插入线圈后，之后再去观察电流表就会看到感应电流，而忽略了磁通量已经停止变化。",
        "错误维度导致错误点出现原因": "学生在推理过程中未能严格分析“什么时候产生感应电流”，遗漏了磁铁插入停止后磁通量不再变化，导致感应电流只在插入瞬间产生、观察时并无指针变化的关键环节，因此做出了错误判断。",
        "main": 0,
        "index": 1
    },
    {
        "错误维度": ["策略性"],
        "典型表现": ["模式识别失败"],
        "具体错误点": "学生未能识别D项涉及典型的“互感现象”，忽视了变化的磁通量引起感应电流，错误选择B项认为两线圈靠近就能感应到电流。",
        "错误维度导致错误点出现原因": "学生缺乏整体观或典型实验模式的识别能力，未能将D项与电磁感应教材中的标准‘互感’实验进行对应，而是凭“线圈彼此靠近也许能互感”的表面印象误选B项。",
        "main": 1,
        "index": 2
    },
    {
        "错误维度": ["执行性"],
        "典型表现": ["审题不清"],
        "具体错误点": "学生理解题目时遗漏了D项‘通电或断电瞬间’这一限定条件，误以为只有持续通电才能产生感应电流，因此未选D而选择其他选项。",
        "错误维度导致错误点出现原因": "在审题环节，学生未注意到题干对实验时机的描述，将‘通电或断电瞬间’与‘持续通电’混为一谈，导致对物理过程分析错误，从而遗漏了正确答案。",
        "main": 0,
        "index": 3
    },
    {
        "错误维度": ["知识性", "执行性"],
        "典型表现": ["规律误记", "计算失误"],
        "具体错误点": "学生记混了电磁感应条件，错误地认为B项中只要有通电线圈旁边有闭合线圈就始终有感应电流，结果选择B为正确答案。",
        "错误维度导致错误点出现原因": "学生一方面对电磁感应需要‘磁通量变化’这一知识点记忆模糊，把‘有磁场’和‘有磁场变化’混为一谈，另一方面在审视题目描述时没有留心‘旁边’的线圈没有任何变化操作，从而做出错误判断。两种缺陷共同作用，导致误选B项。",
        "main": 0,
        "index": 4
    },
    {
        "错误维度": ["逻辑性", "策略性"],
        "典型表现": ["不等价变换", "思维僵化"],
        "具体错误点": "学生直接认为B和C实验和D实验没有本质区别，理由是‘都有磁场或电流的变化’，分别选了B或C，将这三项混为一类，没有仔细区分每种实验的前提和过程，选错答案。",
        "错误维度导致错误点出现原因": "学生缺乏必要的逻辑分析习惯，将发生在不同条件下的实验现象粗暴地等同，忽略了关键物理量——磁通量变化——的特定条件；同时缺乏策略性分析，未能针对每个选项重建物理过程，思维定势导致他们未细致梳理题干各项描述的异同，最终导致答案错误。",
        "main": 0,
        "index": 5
    }
]