[
    {
        "错误维度": ["知识性"],
        "典型表现": ["概念混淆", "规律误记"],
        "具体错误点": "学生认为选项A“气体吸热后温度一定升高”是正确选项，将A包括在答案中，最终答案写为“ABDE”。",
        "错误维度导致错误点出现原因": "学生对热力学第一定律的理解不准确，忽略了气体吸热时如果对外做功，内能的增加可能被做功抵消，从而温度不一定升高。这种知识性错误源于对能量守恒和能量转化途径的知识缺乏或误解，把吸热和温度升高机械等同起来。",
        "main": 0,
        "index": 0
    },
    {
        "错误维度": ["逻辑性"],
        "典型表现": ["分类讨论不完备"],
        "具体错误点": "学生认为选项C“理想气体等压膨胀过程一定放热”正确，将C纳入答案，最终写为“BCDE”。",
        "错误维度导致错误点出现原因": "学生推理过程中忽视了内能的变化规律，仅仅根据体积增大、对外做功就下结论“等压膨胀一定放热”，没有对状态方程中的热、功、内能三者关系进行严谨讨论，逻辑上出现了分类思考不全面的问题。",
        "main": 0,
        "index": 1
    },
    {
        "错误维度": ["策略性"],
        "典型表现": ["思维僵化", "模式识别失败"],
        "具体错误点": "学生只选D，未识别出B和E也是正确项，答案写为“D”",
        "错误维度导致错误点出现原因": "学生解选择题时过于依赖“最常见说法”，习惯性地只在所有选项中挑选最熟悉的（热力学第二定律），忽视了对其余选项逐条分析和比较，缺乏系统的全局解题策略，导致失去了正确答案的其他项。",
        "main": 1,
        "index": 2
    },
    {
        "错误维度": ["执行性"],
        "典型表现": ["抄写错误", "审题不清"],
        "具体错误点": "虽然学生分析正确，但最终答案写成“BCE”，误将“C”写入，漏掉“D”。",
        "错误维度导致错误点出现原因": "学生可能在抄写或填写最终答案时，眼手不协调，把应该选的选项写错，或在核查答案时漏掉关键项。这属于典型的操作环节疏忽，与知识和逻辑无直接关系。",
        "main": 0,
        "index": 3
    },
    {
        "错误维度": ["知识性", "策略性"],
        "典型表现": ["公式错用", "缺乏整体观"],
        "具体错误点": "学生将选项E误判为错误项，答案写为“BD”",
        "错误维度导致错误点出现原因": "学生对于热力学零定律理解不牢，未能认识到关于第三方系统判断热平衡的普适性（知识性），同时解题时缺乏整体通盘分析，只关注热力学第一、第二定律，忽略热平衡法则（策略性），两者共同导致放弃了E项。",
        "main": 0,
        "index": 4
    },
    {
        "错误维度": ["逻辑性", "执行性"],
        "典型表现": ["不等价变换", "计算失误"],
        "具体错误点": "学生在分析过程中，错误推理为：“D说法和C其实是等价的”，因此同时选或同时不选，最终答案为“BCE”。",
        "错误维度导致错误点出现原因": "学生在逻辑推导时将两个本质不同的物理表述（自发热传递与等压膨胀放热）视为等价，把不同热力学定律混为一谈（逻辑性错误）；在具体选择时，误把C当作D，从而因读题疏漏而把C误勾选（执行性错误），逻辑和操作偏差叠加，导致整体错选。",
        "main": 0,
        "index": 5
    }
]