[
    {
        "错误维度": ["知识性错误", "策略性错误"],
        "典型表现": ["概念混淆", "模型选择错误"],
        "具体错误点": "在（1）题回答中，学生认为‘杂合子通常表现的性状是中间型性状’。",
        "错误维度导致错误点出现原因": "学生由于对遗传学基础知识掌握不牢，对‘显性’和‘中间型遗传’两种遗传模式的概念产生混淆（知识性错误——概念混淆），在回忆杂合子性状表现时混淆了完全显性遗传和不完全显性的模型（策略性错误——模型选择错误），导致错误地写出‘中间型性状’作为答案。",
        "main": 1,
        "index": 0
    },
    {
        "错误维度": ["知识性错误", "逻辑性错误"],
        "典型表现": ["结构功能混淆", "推理链断裂"],
        "具体错误点": "在（2）某一思路中，学生将饱满玉米粒和凹陷玉米粒直接杂交，预期子代表现为全部饱满，且以此得出遵循分离定律。",
        "错误维度导致错误点出现原因": "由于学生对玉米粒的基因型与性状表达关系理解不清，混淆了杂合子的显隐性表现（知识性错误——结构功能混淆），同时在推理杂交结果时没有考虑亲本性状对应的遗传型及测交原理，遗漏了对亲本基因型的分类讨论（逻辑性错误——推理链断裂），导致得到全部子代表现为饱满的错误预期，进而无法正确说明分离定律。",
        "main": 0,
        "index": 1
    },
    {
        "错误维度": ["知识性错误", "执行性错误"],
        "典型表现": ["前提条件忽视", "审题不清"],
        "具体错误点": "在回答（2）思路2时，学生没有明确说明是将饱满的玉米粒与凹陷的玉米粒进行测交，仅笼统地写‘让两者杂交’，未能区分自交和测交，导致实验思路模糊。",
        "错误维度导致错误点出现原因": "学生没有注意到分离定律需要通过特定的杂交方式验证（知识性错误——前提条件忽视），加上审题时对‘验证分离定律’应该选择何种杂交方式不敏感（执行性错误——审题不清），最终导致实验步骤设计不清晰，无法有效验证分离定律。",
        "main": 0,
        "index": 2
    },
    {
        "错误维度": ["策略性错误"],
        "典型表现": ["思维僵化"],
        "具体错误点": "在（2）题两种思路答案中，学生只写了自交思路，遗漏杂交/测交思路，只给出‘自交出现3:1分离比’，未提及第二种验证方式及预期结果。",
        "错误维度导致错误点出现原因": "学生在解题方法选择上缺乏对题目多角度的整体把握（策略性错误——思维僵化），只记住了自交可以验证分离定律，没有联想到和掌握常用的‘测交/杂交’也是重要思路，导致答案片面、不完整。",
        "main": 0,
        "index": 3
    }
]