[
    {
        "错误维度": ["知识性错误", "逻辑性错误"],
        "典型表现": ["公式错用", "推理链断裂"],
        "具体错误点": "学生认为动能变为4倍，则水平距离也增加4倍，直接选择D（4倍）作为答案。",
        "错误维度导致错误点出现原因": "由于学生对平抛运动与动能的关系理解不深刻（知识性错误），将动能的变化直接等同于水平射程的线性变化（公式错用）。同时，在推理过程中缺乏对速度与射程关系的分析，未能意识到应先由动能求速度，再通过平抛运动的公式推理（推理链断裂）。因此学生机械地将4倍动能与4倍距离画等号，导致错误判断。",
        "main": 1,
        "index": 0
    },
    {
        "错误维度": ["知识性错误", "策略性错误"],
        "典型表现": ["概念混淆", "模型选择错误"],
        "具体错误点": "学生误以为动能增大只影响速度，不影响射程，认为在空气阻力忽略下小车会落回甲板正下方，水平距离不变，选A（0.25倍）或B（0.5倍）。",
        "错误维度导致错误点出现原因": "学生对平抛运动的基础特征混淆（知识性错误），没有明确区分动能变化对水平速度与水平射程的影响，甚至误解为只影响动能不影响位移（概念混淆）。同时，在解题策略上采用了错误模型，即忽视了平抛运动的分解思想，也没有联想到射程和速度的乘积关系（模型选择错误），由此作出选A或B的低估水平距离的决定。",
        "main": 0,
        "index": 1
    },
    {
        "错误维度": ["策略性错误", "执行性错误"],
        "典型表现": ["思维僵化", "计算失误"],
        "具体错误点": "学生正确求得动能4倍对应速度2倍，但在计算距离时误以为是速度平方成正比，计算得距离为4倍，选D（4倍）。",
        "错误维度导致错误点出现原因": "学生虽然能通过动能公式正确得到速度是2倍，但在后续思维中未能跳出“动能与位移成正比”的僵化模式（思维僵化），同时在数学运算的等比例理解上出错（计算失误），认为距离也应以动能增长的平方成正比，由此得到4倍的错误结论。",
        "main": 0,
        "index": 2
    },
    {
        "错误维度": ["执行性错误"],
        "典型表现": ["审题不清", "抄写错误"],
        "具体错误点": "学生将题目中的‘动能变为4倍’误抄或误看为‘速度变为4倍’，从而计算距离时认为是4倍，选D（4倍）。",
        "错误维度导致错误点出现原因": "在读题环节出现粗心或理解失误（审题不清），将‘动能变为4倍’直接看成‘速度变为4倍’，没有做区分和换算（抄写错误）。因此在后续推理完全基于速度4倍理解，结果将落点距离也写为4倍，选D。",
        "main": 0,
        "index": 3
    },
    {
        "错误维度": ["知识性错误"],
        "典型表现": ["前提条件忽视"],
        "具体错误点": "学生忘记忽略空气阻力的前提，错误地认为随着速度增大，空气阻力随之变大，所以横向距离反而变小，选B（0.5倍）。",
        "错误维度导致错误点出现原因": "由于学生忽视了题目明确给出的‘忽略空气阻力’这一前提条件（前提条件忽视），将现实中的空气阻力效应混入题目解答，错误地认为速度越大阻力损耗越大，导致射程变小，从而得出选项B（0.5倍）的错误答案。",
        "main": 0,
        "index": 4
    }
]