[
    {
        "错误维度": ["知识性错误", "逻辑性错误"],
        "典型表现": ["概念混淆", "推理链断裂"],
        "具体错误点": "学生在判断选项A时，错误认为激素都是由氨基酸通过肽键连接而成，选择了A作为正确答案。",
        "错误维度导致错误点出现原因": "学生对'激素'种类的知识不扎实，忽略了激素包括蛋白质类、类固醇类等多种类型（知识性错误——概念混淆），加上在解题时推理过程不严密，未逐条分析激素种类（逻辑性错误——推理链断裂），因而想当然地把激素与蛋白质画上等号，看到‘肽键’就轻率选择了A。",
        "main": 1,
        "index": 0
    },
    {
        "错误维度": ["知识性错误", "策略性错误"],
        "典型表现": ["前提条件忽视", "缺乏整体观"],
        "具体错误点": "学生在判断选项D时，错误地认为糖原、脂肪、核酸都是身体里的主要能源物质，选择了D作为正确答案。",
        "错误维度导致错误点出现原因": "学生对核酸的功能定位不准确（知识性错误——前提条件忽视），忽视了其主要是遗传信息的载体而不是能源物质。同时他并未整体分析各类物质的主要作用（策略性错误——缺乏整体观），所以一看到‘主要能源物质’就简单联想到都是有机物，从而错误作答。",
        "main": 0,
        "index": 1
    },
    {
        "错误维度": ["策略性错误", "执行性错误"],
        "典型表现": ["模型选择错误", "审题不清"],
        "具体错误点": "学生理解题干时将每个物质的类别混淆，如把脂肪误认为生物大分子，导致选B。",
        "错误维度导致错误点出现原因": "学生对生物大分子的模型划分理解不准确（策略性错误——模型选择错误），解题时细节审查不严（执行性错误——审题不清），没有认真分析脂肪是否是生物大分子，进而错误地将其归入大分子类，选了B。",
        "main": 0,
        "index": 2
    },
    {
        "错误维度": ["知识性错误", "执行性错误"],
        "典型表现": ["生物过程误记", "抄写错误"],
        "具体错误点": "学生在判断选项C时，遗漏了核酸也由含氮单体连接的信息，最终未选择C，或由于抄写错误选择了错误答案。",
        "错误维度导致错误点出现原因": "学生对核酸的组成单元遗忘（知识性错误——生物过程误记），加之在抄答案时出现失误（执行性错误——抄写错误），导致明明判断时发现C正确，却把答案填成了别的选项。",
        "main": 0,
        "index": 3
    }
]